[
    {
        "title": "Launch",
        "type": "feature",
        "date": "2019-04-30T00:00:00",
        "description": "Read about the launch at <a href='https://medium.com/mycrypto/introducing-defiscan-io-40b8d2c3d445' target='_blank' rel='nofollow'>https://medium.com/mycrypto/introducing-defiscan-io-40b8d2c3d445</a>"
    },
    {
        "title": "Uniswap numbers fixed",
        "type": "fix",
        "date": "2019-04-30T01:00:00",
        "description": "Fixed an issue that incorrectly calculated the pool value and pool share"
    },
    {
        "title": "Added public changelog",
        "type": "vanity",
        "date": "2019-05-01T00:00:00",
        "description": "The changelog is now public, displayed in this drawer!"
    },
    {
        "title": "Search box clearing",
        "type": "fix",
        "date": "2019-05-01T01:00:00",
        "description": "Converted the input to a <code>search</code> type to have better experience for mobile users"
    },
    {
        "title": "Allow own node querying",
        "type": "feature",
        "date": "2019-05-03T00:00:00",
        "description": "If you are viewing Defiscan that injects a Web3 instance, it will use that instance - no need to trust a node that Defiscan uses by default. Notice of using injected web3 instance is displayed in the footer."
    },
    {
        "title": "USD Pricing",
        "type": "feature",
        "date": "2019-05-07T00:00:00",
        "description": "You can now see the USD value of your holdings and total pool sizes! Pricing feeds are fetched from nomics and cached in an API."
    }      
]
  
